{
    "parameters": {
        "network_name": "irefindex9",
        "display_name_file": null,
        "output_directory": "result",
        "network_files": [
            "/Volumes/Data/hotnet2/paper/data/networks/hint+hi2012/hint+hi2012_ppr_0.4.h5",
            "/Volumes/Data/hotnet2/paper/data/networks/irefindex9/irefindex9_ppr_0.45.h5",
            "/Volumes/Data/hotnet2/paper/data/networks/multinet/multinet_ppr_0.5.h5"
        ],
        "heat_name": "pan12.mutsig",
        "delta": 0.016878019769251906,
        "consensus_permutations": 0,
        "permuted_network_paths": [
            "/Volumes/Data/hotnet2/paper/data/networks/hint+hi2012/permuted/hint+hi2012_ppr_0.4_##NUM##.h5",
            "/Volumes/Data/hotnet2/paper/data/networks/irefindex9/permuted/irefindex9_ppr_0.45_##NUM##.h5",
            "/Volumes/Data/hotnet2/paper/data/networks/multinet/permuted/multinet_ppr_0.5_##NUM##.h5"
        ],
        "heat_files": [
            "/Volumes/Data/hotnet2/paper/data/heats/pan12.gene2freq.json",
            "/Volumes/Data/hotnet2/paper/data/heats/pan12.gene2mutsig.json"
        ],
        "output_hierarchy": false,
        "num_cores": -1,
        "heat_permutations": 100,
        "display_score_file": null,
        "verbose": 1,
        "deltas": null,
        "min_cc_size": 2,
        "display_score_fil": null,
        "network_permutations": 100
    },
    "sizes": {
        "4": 1,
        "2": 9,
        "3": 3,
        "60": 1
    },
    "components": [
        [
            "ADNP",
            "APC",
            "ARID1A",
            "ARID2",
            "ATM",
            "AXIN2",
            "BRAF",
            "CAB39L",
            "CARD11",
            "CASP8",
            "CBFB",
            "CDKN1A",
            "CDKN1B",
            "CDKN2A",
            "CEBPA",
            "CHD8",
            "CTCF",
            "DCLRE1A",
            "DNMT3A",
            "EZH1",
            "EZH2",
            "FBXW7",
            "GPS2",
            "HRAS",
            "ING1",
            "KDM6A",
            "KEAP1",
            "KIT",
            "KLHL8",
            "KRAS",
            "MAP2K4",
            "MAP3K1",
            "MLL2",
            "MLL3",
            "MLL4",
            "MYCN",
            "NCOR1",
            "NF1",
            "NFE2L2",
            "NOTCH1",
            "NOTCH2",
            "NPM1",
            "NRAS",
            "PBRM1",
            "PIK3CA",
            "PIK3R1",
            "PLCE1",
            "PTEN",
            "RAD21",
            "RASA1",
            "RB1",
            "RUNX1",
            "SHOC2",
            "SMARCA4",
            "SMARCB1",
            "STAG2",
            "STK11",
            "TBL1XR1",
            "TRIP12",
            "WT1"
        ],
        [
            "B2M",
            "CD1D",
            "HLA-A",
            "HLA-B"
        ],
        [
            "ASXL1",
            "ASXL2",
            "BAP1"
        ],
        [
            "CDH1",
            "GNA13",
            "PLEKHA7"
        ],
        [
            "CREBBP",
            "EP300",
            "TP53"
        ],
        [
            "AGFG2",
            "EPS15L1"
        ],
        [
            "EGFR",
            "ERBB2"
        ],
        [
            "MTM1",
            "MTMR12"
        ],
        [
            "MTMR4",
            "TBRG4"
        ],
        [
            "MYD88",
            "SPOP"
        ],
        [
            "POU2AF1",
            "POU2F2"
        ],
        [
            "RAC1",
            "RHOA"
        ],
        [
            "SF3B1",
            "U2AF1"
        ],
        [
            "SMAD2",
            "SMAD4"
        ]
    ],
    "statistics": {
        "2": {
            "observed": 14,
            "pval": 0.41,
            "expected": 12.97
        },
        "3": {
            "observed": 5,
            "pval": 0.18,
            "expected": 3.0
        },
        "4": {
            "observed": 2,
            "pval": 0.27,
            "expected": 1.02
        },
        "5": {
            "observed": 1,
            "pval": 0.41,
            "expected": 0.51
        },
        "6": {
            "observed": 1,
            "pval": 0.17,
            "expected": 0.2
        },
        "7": {
            "observed": 1,
            "pval": 0.11,
            "expected": 0.12
        },
        "8": {
            "observed": 1,
            "pval": 0.03,
            "expected": 0.03
        },
        "9": {
            "observed": 1,
            "pval": 0.01,
            "expected": 0.01
        },
        "10": {
            "observed": 1,
            "pval": 0.01,
            "expected": 0.01
        }
    }
}